CHANGELOG.txt
MANIFEST.in
README.txt
setup.py
TKlighter/__init__.py
Tklighter.egg-info/PKG-INFO
Tklighter.egg-info/SOURCES.txt
Tklighter.egg-info/dependency_links.txt
Tklighter.egg-info/top_level.txt