Metadata-Version: 1.1
Name: Tklighter
Version: 0.0.1
Summary: Adds syntaxhighlighing to tkinter Text
Home-page: https://github.com/Rogers-Kabuye0/TKlighter.git
Author: Rogers Kabuye
Author-email: rogerskabuye0@gmail.com
License: Apache License
Keywords: _h
Platform: UNKNOWN
Classifier: Programming Language :: Python :: 3.6
Classifier: Programming Language :: Python :: 3.7
Classifier: Programming Language :: Python :: 3.8
Classifier: Programming Language :: Python :: 3.9
